xj_migrate/__init__.py
xj_migrate/admin.py
xj_migrate/apps.py
xj_migrate/common.py
xj_migrate/models.py
xj_migrate/urls.py
xj_migrate/apis/__init__.py
xj_migrate/apis/data_migration.py
xj_migrate/services/DataConsolidation.py
xj_migrate/services/__init__.py
xj_database-1.0.0.dist-info/METADATA
xj_database-1.0.0.dist-info/WHEEL
xj_database-1.0.0.dist-info/top_level.txt
xj_database-1.0.0.dist-info/RECORD
