Metadata-Version: 2.1
Name: xj-database
Version: 1.0.0
Summary: 数据库管理模块
Home-page: UNKNOWN
License: apache 3.0
Platform: UNKNOWN
Requires-Dist: python-alipay-sdk
